kisters/network_store/client/network/__init__.py
kisters/network_store/client/network/network.py
kisters/network_store/client/network_store/__init__.py
kisters/network_store/client/network_store/network_store.py
kisters.network_store.client.network-0.4.2.dist-info/AUTHORS.md
kisters.network_store.client.network-0.4.2.dist-info/LICENSE
kisters.network_store.client.network-0.4.2.dist-info/METADATA
kisters.network_store.client.network-0.4.2.dist-info/WHEEL
kisters.network_store.client.network-0.4.2.dist-info/top_level.txt
kisters.network_store.client.network-0.4.2.dist-info/RECORD
