Metadata-Version: 2.1
Name: kisters.network-store.client.network
Version: 0.4.2
Summary: Client library for the Kisters Network Store service
Home-page: https://gitlab.com/kisters/network-store/client
Author: Jesse VanderWees
Author-email: jesse.vanderwees@kisters-bv.nl
License: UNKNOWN
Platform: UNKNOWN
Classifier: Programming Language :: Python :: 3.6
Classifier: Programming Language :: Python :: 3.7
Classifier: Programming Language :: Python :: 3.8
Classifier: Programming Language :: Python :: 3.9
Classifier: License :: OSI Approved :: GNU Lesser General Public License v2 or later (LGPLv2+)
Classifier: Operating System :: OS Independent
Requires-Dist: kisters.network-store.model-library (>=0.2.6)
Requires-Dist: kisters.water.rest-client (>=0.0.8)
Provides-Extra: test
Requires-Dist: kisters.network-store.model-library.water (>=0.2.8) ; extra == 'test'
Requires-Dist: pytest ; extra == 'test'
Provides-Extra: water
Requires-Dist: kisters.network-store.model-library.water (>=0.2.8) ; extra == 'water'
